sksearchspace/__init__.py
sksearchspace/_config.py
sksearchspace/_paths.py
sksearchspace-2020.8.0.0.23.1.dist-info/LICENSE
sksearchspace-2020.8.0.0.23.1.dist-info/METADATA
sksearchspace-2020.8.0.0.23.1.dist-info/WHEEL
sksearchspace-2020.8.0.0.23.1.dist-info/top_level.txt
sksearchspace-2020.8.0.0.23.1.dist-info/zip-safe
sksearchspace-2020.8.0.0.23.1.dist-info/RECORD
