Metadata-Version: 2.1
Name: sksearchspace
Version: 2020.8.0.0.23.1
Summary: Defines search spaces for scikit-lean estimators
Home-page: https://github.com/thomasjpfan/sksearchspace
Author: Thomas J. Fan
Author-email: thomasjpfan@gmail.com
License: MIT
Platform: UNKNOWN
Requires-Python: >=3.6
Requires-Dist: scikit-learn (==0.23.1)
Requires-Dist: ConfigSpace (>=0.4.13)
